{
    "id":  "game:iron_trapdoor",
    "components":  {
                       "block":  {
                                     "solid":  true,
                                     "hardness":  3,
                                     "resistance":  6,
                                     "breakable":  true
                                 },
                       "stack":  {
                                     "max":  64
                                 },
                       "model":  {
                                     "texture":  [
                                                     "iron_trapdoor"
                                                 ],
                                     "textures":  {
                                                      "side":  [
                                                                   "iron_trapdoor"
                                                               ],
                                                      "top":  [
                                                                  "iron_trapdoor"
                                                              ],
                                                      "bottom":  [
                                                                     "iron_trapdoor"
                                                                 ]
                                                  },
                                     "fallback":  {
                                                      "side":  "#8b5a2b",
                                                      "top":  "#8b5a2b",
                                                      "bottom":  "#8b5a2b",
                                                      "default":  "#8b5a2b"
                                                  }
                                 }
                   }
}
