{
    "id":  "game:white_carpet",
    "components":  {
                       "block":  {
                                     "solid":  false,
                                     "hardness":  0.1,
                                     "resistance":  0.1,
                                     "breakable":  true
                                 },
                       "stack":  {
                                     "max":  64
                                 },
                       "model":  {
                                     "texture":  [
                                                     "white_wool"
                                                 ],
                                     "textures":  {
                                                      "side":  [
                                                                   "white_wool"
                                                               ],
                                                      "top":  [
                                                                  "white_wool"
                                                              ],
                                                      "bottom":  [
                                                                     "white_wool"
                                                                 ]
                                                  },
                                     "fallback":  {
                                                      "side":  "#f9fffe",
                                                      "top":  "#f9fffe",
                                                      "bottom":  "#f9fffe",
                                                      "default":  "#f9fffe"
                                                  }
                                 }
                   }
}
